Metadata-Version: 1.0
Name: cgf-ml-sdk
Version: 0.0.8
Summary: cgf_ml_sdk
Home-page: https://gitee.com/AlwaysLee/cgf-ml_sdk-python.git
Author: cgf_ml_sdk
Author-email: 512070806@qq.com
License: MIT
Platform: UNKNOWN
